PyWebUI/App.py
PyWebUI/Constants.py
PyWebUI/Frontend.py
PyWebUI/Functions.py
PyWebUI/Globals.py
PyWebUI/Launcher_android.py
PyWebUI/Launcher_windows.py
PyWebUI/__init__.py
PyWebUI/pywebui.py
cross.pywebui-0.0.0.1.dist-info/METADATA
cross.pywebui-0.0.0.1.dist-info/WHEEL
cross.pywebui-0.0.0.1.dist-info/top_level.txt
cross.pywebui-0.0.0.1.dist-info/RECORD
